{
  "year": 1958,
  "driverChampion": {
    "name": "Mike Hawthorn",
    "team": "Ferrari",
    "points": 42.0
  },
  "constructorChampion": {
    "name": "Vanwall",
    "points": 48.0
  },
  "races": [
    {
      "round": 1,
      "name": "Argentine Grand Prix",
      "circuit": "Buenos Aires",
      "country": "Argentina",
      "date": "1958-01-19",
      "winner": "Stirling Moss",
      "team": "Cooper"
    },
    {
      "round": 2,
      "name": "Monaco Grand Prix",
      "circuit": "Monte Carlo",
      "country": "Monaco",
      "date": "1958-05-18",
      "winner": "Maurice Trintignant",
      "team": "Cooper"
    },
    {
      "round": 3,
      "name": "Dutch Grand Prix",
      "circuit": "Zandvoort",
      "country": "Netherlands",
      "date": "1958-05-26",
      "winner": "Stirling Moss",
      "team": "Vanwall"
    },
    {
      "round": 4,
      "name": "Indianapolis 500",
      "circuit": "Indianapolis",
      "country": "USA",
      "date": "1958-05-30",
      "winner": "Jimmy Bryan",
      "team": "Epperly"
    },
    {
      "round": 5,
      "name": "Belgian Grand Prix",
      "circuit": "Spa",
      "country": "Belgium",
      "date": "1958-06-15",
      "winner": "Tony Brooks",
      "team": "Vanwall"
    },
    {
      "round": 6,
      "name": "French Grand Prix",
      "circuit": "Reims",
      "country": "France",
      "date": "1958-07-06",
      "winner": "Mike Hawthorn",
      "team": "Ferrari"
    },
    {
      "round": 7,
      "name": "British Grand Prix",
      "circuit": "Silverstone",
      "country": "UK",
      "date": "1958-07-19",
      "winner": "Peter Collins",
      "team": "Ferrari"
    },
    {
      "round": 8,
      "name": "German Grand Prix",
      "circuit": "N\u00fcrburg",
      "country": "Germany",
      "date": "1958-08-03",
      "winner": "Tony Brooks",
      "team": "Vanwall"
    },
    {
      "round": 9,
      "name": "Portuguese Grand Prix",
      "circuit": "Oporto",
      "country": "Portugal",
      "date": "1958-08-24",
      "winner": "Stirling Moss",
      "team": "Vanwall"
    },
    {
      "round": 10,
      "name": "Italian Grand Prix",
      "circuit": "Monza",
      "country": "Italy",
      "date": "1958-09-07",
      "winner": "Tony Brooks",
      "team": "Vanwall"
    },
    {
      "round": 11,
      "name": "Moroccan Grand Prix",
      "circuit": "Casablanca",
      "country": "Morocco",
      "date": "1958-10-19",
      "winner": "Stirling Moss",
      "team": "Vanwall"
    }
  ],
  "driverStandings": [
    {
      "position": 1,
      "driver": "Mike Hawthorn",
      "team": "Ferrari",
      "points": 42.0,
      "wins": 1
    },
    {
      "position": 2,
      "driver": "Stirling Moss",
      "team": "Cooper",
      "points": 41.0,
      "wins": 4
    },
    {
      "position": 3,
      "driver": "Tony Brooks",
      "team": "Vanwall",
      "points": 24.0,
      "wins": 3
    },
    {
      "position": 4,
      "driver": "Roy Salvadori",
      "team": "Cooper",
      "points": 15.0,
      "wins": 0
    },
    {
      "position": 5,
      "driver": "Peter Collins",
      "team": "Ferrari",
      "points": 14.0,
      "wins": 1
    },
    {
      "position": 6,
      "driver": "Harry Schell",
      "team": "Maserati",
      "points": 14.0,
      "wins": 0
    },
    {
      "position": 7,
      "driver": "Maurice Trintignant",
      "team": "Cooper",
      "points": 12.0,
      "wins": 1
    },
    {
      "position": 8,
      "driver": "Luigi Musso",
      "team": "Ferrari",
      "points": 12.0,
      "wins": 0
    },
    {
      "position": 9,
      "driver": "Stuart Lewis-Evans",
      "team": "Vanwall",
      "points": 11.0,
      "wins": 0
    },
    {
      "position": 10,
      "driver": "Phil Hill",
      "team": "Maserati",
      "points": 9.0,
      "wins": 0
    },
    {
      "position": 11,
      "driver": "Wolfgang von Trips",
      "team": "Ferrari",
      "points": 9.0,
      "wins": 0
    },
    {
      "position": 12,
      "driver": "Jean Behra",
      "team": "Maserati",
      "points": 9.0,
      "wins": 0
    },
    {
      "position": 13,
      "driver": "Jimmy Bryan",
      "team": "Epperly",
      "points": 8.0,
      "wins": 1
    },
    {
      "position": 14,
      "driver": "Juan Fangio",
      "team": "Maserati",
      "points": 7.0,
      "wins": 0
    },
    {
      "position": 15,
      "driver": "George Amick",
      "team": "Epperly",
      "points": 6.0,
      "wins": 0
    },
    {
      "position": 16,
      "driver": "Johnny Boyd",
      "team": "Kurtis Kraft",
      "points": 4.0,
      "wins": 0
    },
    {
      "position": 17,
      "driver": "Tony Bettenhausen",
      "team": "Epperly",
      "points": 4.0,
      "wins": 0
    },
    {
      "position": 18,
      "driver": "Jack Brabham",
      "team": "Cooper",
      "points": 3.0,
      "wins": 0
    },
    {
      "position": 19,
      "driver": "Cliff Allison",
      "team": "Team Lotus",
      "points": 3.0,
      "wins": 0
    },
    {
      "position": 20,
      "driver": "Jo Bonnier",
      "team": "Maserati",
      "points": 3.0,
      "wins": 0
    },
    {
      "position": 21,
      "driver": "Jim Rathmann",
      "team": "Epperly",
      "points": 2.0,
      "wins": 0
    },
    {
      "position": 0,
      "driver": "Masten Gregory",
      "team": "Maserati",
      "points": 0.0,
      "wins": 0
    },
    {
      "position": 0,
      "driver": "Carroll Shelby",
      "team": "Maserati",
      "points": 0.0,
      "wins": 0
    },
    {
      "position": 0,
      "driver": "Bruce McLaren",
      "team": "Cooper",
      "points": 0.0,
      "wins": 0
    },
    {
      "position": 0,
      "driver": "Graham Hill",
      "team": "Team Lotus",
      "points": 0.0,
      "wins": 0
    },
    {
      "position": 0,
      "driver": "Olivier Gendebien",
      "team": "Ferrari",
      "points": 0.0,
      "wins": 0
    },
    {
      "position": 0,
      "driver": "Jimmy Reece",
      "team": "Watson",
      "points": 0.0,
      "wins": 0
    },
    {
      "position": 0,
      "driver": "Edgar Barth",
      "team": "Porsche",
      "points": 0.0,
      "wins": 0
    },
    {
      "position": 0,
      "driver": "Ian Burgess",
      "team": "Cooper",
      "points": 0.0,
      "wins": 0
    },
    {
      "position": 0,
      "driver": "Carlos Menditeguy",
      "team": "Maserati",
      "points": 0.0,
      "wins": 0
    },
    {
      "position": 0,
      "driver": "Don Freeland",
      "team": "Phillips",
      "points": 0.0,
      "wins": 0
    },
    {
      "position": 0,
      "driver": "Paco Godia",
      "team": "Maserati",
      "points": 0.0,
      "wins": 0
    },
    {
      "position": 0,
      "driver": "Jack Fairman",
      "team": "Connaught",
      "points": 0.0,
      "wins": 0
    },
    {
      "position": 0,
      "driver": "Jud Larson",
      "team": "Watson",
      "points": 0.0,
      "wins": 0
    },
    {
      "position": 0,
      "driver": "Tony Marsh",
      "team": "Cooper",
      "points": 0.0,
      "wins": 0
    },
    {
      "position": 0,
      "driver": "Gerino Gerini",
      "team": "Maserati",
      "points": 0.0,
      "wins": 0
    },
    {
      "position": 0,
      "driver": "Hans Herrmann",
      "team": "Maserati",
      "points": 0.0,
      "wins": 0
    },
    {
      "position": 0,
      "driver": "Horace Gould",
      "team": "Maserati",
      "points": 0.0,
      "wins": 0
    },
    {
      "position": 0,
      "driver": "Eddie Johnson",
      "team": "Kurtis Kraft",
      "points": 0.0,
      "wins": 0
    },
    {
      "position": 0,
      "driver": "Maria de Filippis",
      "team": "Maserati",
      "points": 0.0,
      "wins": 0
    },
    {
      "position": 0,
      "driver": "Troy Ruttman",
      "team": "Maserati",
      "points": 0.0,
      "wins": 0
    },
    {
      "position": 0,
      "driver": "Bill Cheesbourg",
      "team": "Kurtis Kraft",
      "points": 0.0,
      "wins": 0
    },
    {
      "position": 0,
      "driver": "Ivor Bueb",
      "team": "Connaught",
      "points": 0.0,
      "wins": 0
    },
    {
      "position": 0,
      "driver": "Carel Godin de Beaufort",
      "team": "Porsche",
      "points": 0.0,
      "wins": 0
    },
    {
      "position": 0,
      "driver": "Al Keller",
      "team": "Kurtis Kraft",
      "points": 0.0,
      "wins": 0
    },
    {
      "position": 0,
      "driver": "Johnnie Parsons",
      "team": "Kurtis Kraft",
      "points": 0.0,
      "wins": 0
    },
    {
      "position": 0,
      "driver": "Johnnie Tolan",
      "team": "Kuzma",
      "points": 0.0,
      "wins": 0
    },
    {
      "position": 0,
      "driver": "Robert La Caze",
      "team": "Cooper",
      "points": 0.0,
      "wins": 0
    },
    {
      "position": 0,
      "driver": "Andr\u00e9 Guelfi",
      "team": "Cooper",
      "points": 0.0,
      "wins": 0
    },
    {
      "position": 0,
      "driver": "Giulio Cabianca",
      "team": "OSCA",
      "points": 0.0,
      "wins": 0
    },
    {
      "position": 0,
      "driver": "Giorgio Scarlatti",
      "team": "Maserati",
      "points": 0.0,
      "wins": 0
    },
    {
      "position": 0,
      "driver": "Wolfgang Seidel",
      "team": "Maserati",
      "points": 0.0,
      "wins": 0
    },
    {
      "position": 0,
      "driver": "Bob Christie",
      "team": "Kurtis Kraft",
      "points": 0.0,
      "wins": 0
    },
    {
      "position": 0,
      "driver": "Dempsey Wilson",
      "team": "Kuzma",
      "points": 0.0,
      "wins": 0
    },
    {
      "position": 0,
      "driver": "Anthony Foyt",
      "team": "Kuzma",
      "points": 0.0,
      "wins": 0
    },
    {
      "position": 0,
      "driver": "Christian Goethals",
      "team": "Cooper",
      "points": 0.0,
      "wins": 0
    },
    {
      "position": 0,
      "driver": "Ron Flockhart",
      "team": "Cooper",
      "points": 0.0,
      "wins": 0
    },
    {
      "position": 0,
      "driver": "Mike Magill",
      "team": "Kurtis Kraft",
      "points": 0.0,
      "wins": 0
    },
    {
      "position": 0,
      "driver": "Paul Russo",
      "team": "Kurtis Kraft",
      "points": 0.0,
      "wins": 0
    },
    {
      "position": 0,
      "driver": "Alan Stacey",
      "team": "Team Lotus",
      "points": 0.0,
      "wins": 0
    },
    {
      "position": 0,
      "driver": "Fran\u00e7ois Picard",
      "team": "Cooper",
      "points": 0.0,
      "wins": 0
    },
    {
      "position": 0,
      "driver": "Shorty Templeman",
      "team": "Kurtis Kraft",
      "points": 0.0,
      "wins": 0
    },
    {
      "position": 0,
      "driver": "Tom Bridger",
      "team": "Cooper",
      "points": 0.0,
      "wins": 0
    },
    {
      "position": 0,
      "driver": "Rodger Ward",
      "team": "Lesovsky",
      "points": 0.0,
      "wins": 0
    },
    {
      "position": 0,
      "driver": "Billy Garrett",
      "team": "Kurtis Kraft",
      "points": 0.0,
      "wins": 0
    },
    {
      "position": 0,
      "driver": "Eddie Sachs",
      "team": "Kuzma",
      "points": 0.0,
      "wins": 0
    },
    {
      "position": 0,
      "driver": "Dick Gibson",
      "team": "Cooper",
      "points": 0.0,
      "wins": 0
    },
    {
      "position": 0,
      "driver": "Johnny Thomson",
      "team": "Kurtis Kraft",
      "points": 0.0,
      "wins": 0
    },
    {
      "position": 0,
      "driver": "Brian Naylor",
      "team": "Cooper",
      "points": 0.0,
      "wins": 0
    },
    {
      "position": 0,
      "driver": "Chuck Weyant",
      "team": "Dunn",
      "points": 0.0,
      "wins": 0
    },
    {
      "position": 0,
      "driver": "Jack Turner",
      "team": "Lesovsky",
      "points": 0.0,
      "wins": 0
    },
    {
      "position": 0,
      "driver": "Bob Veith",
      "team": "Kurtis Kraft",
      "points": 0.0,
      "wins": 0
    },
    {
      "position": 0,
      "driver": "Dick Rathmann",
      "team": "Watson",
      "points": 0.0,
      "wins": 0
    },
    {
      "position": 0,
      "driver": "Ed Elisian",
      "team": "Watson",
      "points": 0.0,
      "wins": 0
    },
    {
      "position": 0,
      "driver": "Pat O'Connor",
      "team": "Kurtis Kraft",
      "points": 0.0,
      "wins": 0
    },
    {
      "position": 0,
      "driver": "Paul Goldsmith",
      "team": "Kurtis Kraft",
      "points": 0.0,
      "wins": 0
    },
    {
      "position": 0,
      "driver": "Jerry Unser",
      "team": "Kurtis Kraft",
      "points": 0.0,
      "wins": 0
    },
    {
      "position": 0,
      "driver": "Len Sutton",
      "team": "Kurtis Kraft",
      "points": 0.0,
      "wins": 0
    },
    {
      "position": 0,
      "driver": "Art Bisch",
      "team": "Kuzma",
      "points": 0.0,
      "wins": 0
    }
  ],
  "constructorStandings": [
    {
      "position": 1,
      "constructor": "Vanwall",
      "points": 48.0,
      "wins": 6
    },
    {
      "position": 2,
      "constructor": "Ferrari",
      "points": 40.0,
      "wins": 2
    },
    {
      "position": 3,
      "constructor": "Cooper",
      "points": 31.0,
      "wins": 2
    },
    {
      "position": 4,
      "constructor": "BRM",
      "points": 18.0,
      "wins": 0
    },
    {
      "position": 5,
      "constructor": "Maserati",
      "points": 6.0,
      "wins": 0
    },
    {
      "position": 6,
      "constructor": "Team Lotus",
      "points": 3.0,
      "wins": 0
    },
    {
      "position": 0,
      "constructor": "Porsche",
      "points": 0.0,
      "wins": 0
    },
    {
      "position": 0,
      "constructor": "Connaught",
      "points": 0.0,
      "wins": 0
    }
  ]
}